chrome_printtopdf/__init__.py
chrome_printtopdf/__main__.py
chrome_printtopdf/chrome_printtopdf.py
chrome_printtopdf-0.0.2.dist-info/DESCRIPTION.rst
chrome_printtopdf-0.0.2.dist-info/METADATA
chrome_printtopdf-0.0.2.dist-info/RECORD
chrome_printtopdf-0.0.2.dist-info/WHEEL
chrome_printtopdf-0.0.2.dist-info/metadata.json
chrome_printtopdf-0.0.2.dist-info/top_level.txt
